{"name":"White Acacia | Robinia Pseudoacacia # 5 (9.5m)","type":"simple","regular_price":"2","description":"more acacias: https://3dsky.org/collection/shared/5082380 Leaves using opacity map. The barrel material uses a displacement map. Height: 9.5 m Polygons: 3,616,293","short_description":"Platform:\t 3dsMax 2013 + fbx\nRender:\t Corona\nSize:\t 152 MB\nStyle:\t Modern\nMaterials:\t Organics","sku":"2429739.5cc6ced30eef4","categories":[{"name":"Tree"}],"downloadable":true,"downloads":[{"name":"2429739.5cc6ced30eef4","file":"https://www.dropbox.com/scl/fi/62n3kxnbkfxvly68ywv9z/2429739.5cc6ced30eef4.rar?rlkey=nraid35oo9dqa3yoes4aaxnms&dl=1"}],"tags":[{"name":"robinia"},{"name":"acacia"},{"name":"tree"},{"name":"locust"}],"images":[{"src":"https://www.dropbox.com/scl/fi/g1mcj75qdr8mw7fjmwyk7/2429739.5cc6ced30eef4.jpg?rlkey=c4n9g1kp8nzhi3w86h9ymg1np&dl=1"}],"attributes":[{"id":1,"name":"Price","options":["Pro"]},{"id":2,"name":"Render","options":["Corona"]},{"id":3,"name":"Style","options":["Modern"]}]}