{"name":"Branches in vases 34","type":"simple","regular_price":"2","description":"Model good for Luxury space (Kitchen and Living)","short_description":"Platform:\t 3dsMax 2014 + obj\nRender:\t Corona\nSize:\t 78 MB\nStyle:\t Modern\nMaterials:\t Glass, Organics","sku":"2718812.5e4e8d020b4ba","categories":[{"name":"Bouquet"}],"downloadable":true,"downloads":[{"name":"2718812.5e4e8d020b4ba","file":"https://www.dropbox.com/scl/fi/cw2oitd7wn22z80pepbg9/2718812.5e4e8d020b4ba.rar?rlkey=rqavhv3meeob9v4vikh4g7jrr&dl=1"}],"tags":[{"name":"dogwood"},{"name":"branches"},{"name":"green"},{"name":"luxury"},{"name":"flower"},{"name":"blooming"}],"images":[{"src":"https://www.dropbox.com/scl/fi/1i9cp9fhxakkys13smguz/2718812.5e4e8d020b4ba.jpg?rlkey=pdplwilabyffiicss0sc3upzd&dl=1"}],"attributes":[{"id":1,"name":"Price","options":["Pro"]},{"id":2,"name":"Render","options":["Corona"]},{"id":3,"name":"Style","options":["Modern"]}]}