{"name":"Tresse Flat Shower Cabin","type":"simple","regular_price":"2","description":"Manufacturer: Tresse Model: Flat V-ray and Corona materials","short_description":"Platform:\t 3dsMax 2012 + fbx\nRender:\t Vray+Corona\nSize:\t 9 MB\nStyle:\t Modern\nMaterials:\t Metal, Glass","sku":"3229056.6007fab9103d5","categories":[{"name":"Shower"}],"downloadable":true,"downloads":[{"name":"3229056.6007fab9103d5","file":"https://www.dropbox.com/scl/fi/5kqn0rdw11otn2l4adw1r/3229056.6007fab9103d5.rar?rlkey=jlhhbsy4ceszpsg41gxi4ilit&dl=1"}],"tags":[{"name":"shower"},{"name":"cabin"},{"name":"flat"},{"name":"tresse"},{"name":"mixer"},{"name":"glass"},{"name":"metal"},{"name":"plastic"},{"name":"sink"},{"name":"water"},{"name":"drops"}],"images":[{"src":"https://www.dropbox.com/scl/fi/pmj1yyxs9fj2anaokug26/3229056.6007fab9103d5.jpg?rlkey=3jmul5hr0jxk9avk90t6uj3lt&dl=1"}],"attributes":[{"id":1,"name":"Price","options":["Pro"]},{"id":2,"name":"Render","options":["Vray+Corona"]},{"id":3,"name":"Style","options":["Modern"]}]}