{"name":"Indoor Plants Pack 09","type":"simple","regular_price":"2","description":"Indoor Plants Pack 09 This selection of indoor exotic plants will provide a nice touch to your interior renders. I kept the polycount relatively low but you can also subdivide the model if you need more definition. -Licuala Grandis -Thrinax Radiata -Monstera Deliciosa Format: .blend .max .fbx 4k Textures -Vertices 39 813 -Polygons 35 810 -Triangles 71 354 Show more","short_description":"Platform:\t 3dsMax 2014 + fbx\nRender:\t MentalRay\nSize:\t 62 MB\nStyle:\t Modern\nMaterials:\t Concrete, Organics","sku":"3831169.61ad3ee532f51","categories":[{"name":"Indoor"}],"downloadable":true,"downloads":[{"name":"3831169.61ad3ee532f51","file":"https://www.dropbox.com/scl/fi/689eq6o6lnciu4libl2sw/3831169.61ad3ee532f51.rar?rlkey=niko9a9i7h4hvzuoofr2dlsub&dl=1"}],"tags":[{"name":"licuala"},{"name":"grandis"},{"name":"thrinax"},{"name":"radiata"},{"name":"monstera"},{"name":"deliciosa"},{"name":"pot"},{"name":"potted"},{"name":"palm"},{"name":"palmtree"}],"images":[{"src":"https://www.dropbox.com/scl/fi/bgh9kqmchrxa8aqwtqnbm/3831169.61ad3ee532f51.jpg?rlkey=nlimyjel0mdccf3vf5fwl4jix&dl=1"}],"attributes":[{"id":1,"name":"Price","options":["Pro"]},{"id":2,"name":"Render","options":["MentalRay"]},{"id":3,"name":"Style","options":["Modern"]}]}