{"name":"Acrylic Column Table Lamp","type":"simple","regular_price":"2","description":"3ds Max 2010. V-Ray 2.40.03. File formats fbx, obj. 3ds. Acrylic Column Table Lamp. The height of the lamp 64 cm. Polygons: 43373. Vertices: 30925.","short_description":"Platform:\t 3dsMax 2010 + obj\nRender:\t Vray\nSize:\t 32 MB\nStyle:\t Ethnic\nMaterials:\t Fabric, Glass","sku":"597533.57967a6e3ad24","categories":[{"name":"Table lamp"}],"downloadable":true,"downloads":[{"name":"597533.57967a6e3ad24","file":"https://www.dropbox.com/scl/fi/rfuz4mqocugvbgv0y27dz/597533.57967a6e3ad24.rar?rlkey=sa4che6q8ecnxojdbkb92kyfi&dl=1"}],"tags":[{"name":"bird"},{"name":"transparent"},{"name":"table lamp"},{"name":"lamp"},{"name":"shade"},{"name":"light bulb"},{"name":"acrylic column"},{"name":"west elm"}],"images":[{"src":"https://www.dropbox.com/scl/fi/r6u4jfstako9kgnw3uj2j/597533.57967a6e3ad24.jpg?rlkey=p8kymoozniz68w942nomda5tg&dl=1"}],"attributes":[{"id":1,"name":"Price","options":["Pro"]},{"id":2,"name":"Render","options":["Vray"]},{"id":3,"name":"Style","options":["Ethnic"]}]}