{"name":"Sophie Mirrored Dining Table_set","type":"simple","regular_price":"2","description":"Table Sophie Mirrored Dining Table: Dimensions: Width: 84 \"Depth: 40\" Height: 30.5 \"Ware Paramount Dinnerware - Sets of 4 Candlestick Petite Candelabra: Dimensions8.5''H x 8\" Diameter Candlestick Crystal Lotus Candlelight Collection Victoria Cake Stand: Dimensions: 8''H x 9 \"Diameter Victoria Decanter: Dimensions: 7.75''W x 11.5''H Chandelier Eclipse Chandelier - Olde Silver: Dimensions: 35''H x 29\" Diameter Mirror: Grantola Designer: Grace Feyock Dimensions: 48 WX 72 HX 1 D (in) Show more","short_description":"Platform:\t 3dsMax 2013 + fbx\nRender:\t Vray\nSize:\t 93 MB\nStyle:\t Classic\nMaterials:\t Metal, Glass","sku":"840774.5885f26152c32","categories":[{"id":"102"}],"downloadable":true,"downloads":[{"name":"840774.5885f26152c32","file":"https://www.dropbox.com/scl/fi/gzurb0o9olmbcvh209hzm/840774.5885f26152c32.rar?rlkey=8zxn3rp2bv2csevtv9awhs7cu&dl=1"}],"tags":[{"name":"laying"},{"name":"service"},{"name":"cutlery"},{"name":"dishes"},{"name":"plate"},{"name":"wineglass"},{"name":"a spoon"},{"name":"fork"},{"name":"knife"},{"name":"napkin"},{"name":"flowers"},{"name":"vase"},{"name":"bouquet"},{"name":"wine"},{"name":"alcohol"},{"name":"candle"},{"name":"candlestick"},{"name":"hydrangea"}],"images":[{"src":"https://www.dropbox.com/scl/fi/yzdmkep3sk62tk3031v4o/840774.5885f26152c32.jpg?rlkey=3sa7q5v0df3liig3dyvvldr2f&dl=1"}],"attributes":[{"id":1,"name":"Price","options":["Pro"]},{"id":2,"name":"Render","options":["Vray"]},{"id":3,"name":"Style","options":["Classic"]}]}