{"name":"Kitchen Decorative set 09","type":"simple","regular_price":"2","description":"decorative set for the kitchen. The archive scene 3ds max 2014 and file obj. On all objects Turbosmooth. Materials for Corona and Vray. Hope you like it.","short_description":"Platform:\t 3dsMax 2014 + obj\nRender:\t Vray+Corona\nSize:\t 16 MB\nStyle:\t Modern\nMaterials:\t Stone, Organics","sku":"2527339.5d5ee109c0386","categories":[{"name":"Other kitchen accessories"}],"downloadable":true,"downloads":[{"name":"2527339.5d5ee109c0386","file":"https://www.dropbox.com/scl/fi/4cs8v74aea3dndyflfsmb/2527339.5d5ee109c0386.rar?rlkey=jphitmmrze2ornc28kpuxg1s9&dl=1"}],"tags":[{"name":"scandinavian"},{"name":"marble"},{"name":"wicker"},{"name":"kitchenware"},{"name":"packaging"},{"name":"cutting board"},{"name":"egg"},{"name":"cook book"},{"name":"oil"},{"name":"bottle"},{"name":"menu"},{"name":"tray"},{"name":"towel"},{"name":"cup"},{"name":"plate"},{"name":"candles"}],"images":[{"src":"https://www.dropbox.com/scl/fi/okewne3agf2y3p8bx3vcv/2527339.5d5ee109c0386.jpg?rlkey=ei5zq2vr9nt1olzq3jqbs8khx&dl=1"}],"attributes":[{"id":1,"name":"Price","options":["Pro"]},{"id":2,"name":"Render","options":["Vray+Corona"]},{"id":3,"name":"Style","options":["Modern"]}]}