{"name":"Croton plant set 10","type":"simple","regular_price":"2","description":"Croton plant set 10 4 tree and with 1 color height> 0.75 m Fbx and obj (Vray 4.2 and corona 5) Executed in 3d max 2013 All textures and materials needed for the rendering found in the archive Smoothing modifier is stored in the stack for convenience","short_description":"Platform:\t 3dsMax 2013 + obj\nRender:\t Vray+Corona\nSize:\t 67 MB\nStyle:\t Classic\nMaterials:\t Organics","sku":"2989739.5f3a495b7594b","categories":[{"name":"Bush"}],"downloadable":true,"downloads":[{"name":"2989739.5f3a495b7594b","file":"https://www.dropbox.com/scl/fi/uk93k9f8ijlauadil4ehm/2989739.5f3a495b7594b.rar?rlkey=int68uz9l5a08psyl5rz5izje&dl=1"}],"tags":[{"name":"croton"},{"name":"plant"},{"name":"bush"},{"name":"trunk"},{"name":"branch"},{"name":"leaf"},{"name":"leaves"},{"name":"organics"},{"name":"tree"},{"name":"outdoor"},{"name":"landscape"},{"name":"green"}],"images":[{"src":"https://www.dropbox.com/scl/fi/4fwsa7de82lytujg994q6/2989739.5f3a495b7594b.jpg?rlkey=et6uf37hi3fgvguma4cg6jznq&dl=1"}],"attributes":[{"id":1,"name":"Price","options":["Pro"]},{"id":2,"name":"Render","options":["Vray+Corona"]},{"id":3,"name":"Style","options":["Classic"]}]}