{"name":"DINING TABLE 9","type":"simple","regular_price":"2","description":"DINING TABLE WITH SET OF 2,4,6 SEATINGS","short_description":"Platform:\t 3dsMax 2015 + fbx\nRender:\t Vray\nSize:\t 1 MB\nStyle:\t Modern\nMaterials:\t Wood, Plastic","sku":"332541.55cb6430490a3","categories":[{"name":"Table + Chair 1"}],"downloadable":true,"downloads":[{"name":"332541.55cb6430490a3","file":"https://www.dropbox.com/scl/fi/9xhjov0v4stgc43h900ym/332541.55cb6430490a3.rar?rlkey=dl7lcat04vpad21pi5fgvzhfq&dl=1"}],"tags":[{"name":"dining"}],"images":[{"src":"https://www.dropbox.com/scl/fi/sn40pysus8io4la2r832t/332541.55cb6430490a3.jpg?rlkey=ld49awm23nd6b5v3vxmfi64lr&dl=1"}],"attributes":[{"id":1,"name":"Price","options":["Pro"]},{"id":2,"name":"Render","options":["Vray"]},{"id":3,"name":"Style","options":["Modern"]}]}