{"name":"mamas & papas","type":"simple","regular_price":"2","description":"Polygonal modeling with anti-aliasing. UV unwrapping at all sites Just have a .max file configured for imaging in the corona renderer","short_description":"Platform:\t 3dsMax 2013 + fbx\nRender:\t Vray\nSize:\t 44 MB\nStyle:\t Modern\nMaterials:\t Wood, Fabric","sku":"633287.57da4b8ac4a97","categories":[{"name":"Bed 1"}],"downloadable":true,"downloads":[{"name":"633287.57da4b8ac4a97","file":"https://www.dropbox.com/scl/fi/az7iljrkrebjkaxx8zt4c/633287.57da4b8ac4a97.rar?rlkey=a3d3g54yzvpxmrbsdolvmwc8u&dl=1"}],"tags":[{"name":"cot"},{"name":"changing"},{"name":"table"}],"images":[{"src":"https://www.dropbox.com/scl/fi/em7l34gfwxe3v6xlq5svg/633287.57da4b8ac4a97.jpg?rlkey=vwlbyard9vmdd7geyrfx1ommz&dl=1"}],"attributes":[{"id":1,"name":"Price","options":["Pro"]},{"id":2,"name":"Render","options":["Vray"]},{"id":3,"name":"Style","options":["Modern"]}]}