{"name":"Door VOSTOK 4X V3","type":"simple","regular_price":"2","description":"Door made in the east (ethnic) style. The archive is a version CORONA 2014, Vray 2011. previews have 3000h3000px Preview to review the file in the model https://drive.google.com/open?id=0Bxro-vP_fwplUXlvSGgza09JSzg","short_description":"Platform:\t 3dsMax 2011 + obj\nRender:\t Vray\nSize:\t 62 MB\nStyle:\t Ethnic\nMaterials:\t Wood","sku":"844868.5888ab085fa42","categories":[{"id":"162"}],"downloadable":true,"downloads":[{"name":"844868.5888ab085fa42","file":"https://www.dropbox.com/scl/fi/8o307j4pxqc3qajaknpj8/844868.5888ab085fa42.rar?rlkey=ndn5379zhgatumj2o2x2h0xbe&dl=1"}],"tags":[{"name":"east"},{"name":"arab"},{"name":"door"}],"images":[{"src":"https://www.dropbox.com/scl/fi/8f9xnl6l6lfl5769ztx8s/844868.5888ab085fa42.jpg?rlkey=we4h6hje7f51ne1m5jpi378t4&dl=1"}],"attributes":[{"id":1,"name":"Price","options":["Pro"]},{"id":2,"name":"Render","options":["Vray"]},{"id":3,"name":"Style","options":["Ethnic"]}]}