{"name":"DITRE ITALIA St. Germain Leather Sofa","type":"simple","regular_price":"2","description":"Sofa DITRE ITALIA St. Germain 273 x 104 x 70 cm Table DITRE ITALIA St. Germain 100 x 100 x 35 cm 40 x 50 x 50 cm Plaid Crate & Barrel Landyn Blue Chunky Knit Throw in the file for Vray 1.5 VrayFur no modifier. The archive: * .max 2011 with materials for Vray 3.0; * .max 2011 with materials for Vray 1.5; * .FBX; * .tekstury And previews.","short_description":"Platform:\t 3dsMax 2011 + fbx\nRender:\t Vray\nSize:\t 88 MB\nStyle:\t Ethnic\nMaterials:\t Leather","sku":"927729.58bc8a7220405","categories":[{"id":"72"}],"downloadable":true,"downloads":[{"name":"927729.58bc8a7220405","file":"https://www.dropbox.com/scl/fi/lb201ffk2nmhszyzmbx6v/927729.58bc8a7220405.rar?rlkey=c61ewj2pd5v2gtzptvyijhwuf&dl=1"}],"tags":[{"name":"ditre italia"},{"name":"st. germain"},{"name":"crate and barrel"},{"name":"crate&barrel"},{"name":"plaid"},{"name":"pillow"},{"name":"leather"},{"name":"coffee"},{"name":"book"},{"name":"carpet"}],"images":[{"src":"https://www.dropbox.com/scl/fi/lql6z2m0tkqloqiknhzro/927729.58bc8a7220405.jpg?rlkey=p7mqubovrctheegz2kw9vtdxm&dl=1"}],"attributes":[{"id":1,"name":"Price","options":["Pro"]},{"id":2,"name":"Render","options":["Vray"]},{"id":3,"name":"Style","options":["Ethnic"]}]}